DBoW3Py.cpython-37m-darwin.so
libDBoW3.0.0.1.dylib
libDBoW3.0.0.dylib
libDBoW3.dylib
DBoW3Py-0.0.4.dist-info/LICENSE.txt
DBoW3Py-0.0.4.dist-info/METADATA
DBoW3Py-0.0.4.dist-info/WHEEL
DBoW3Py-0.0.4.dist-info/top_level.txt
DBoW3Py-0.0.4.dist-info/RECORD
