Metadata-Version: 2.1
Name: DBoW3Py
Version: 0.0.4
Summary: python wrapper of DBoW3
Home-page: https://github.com/Cenbylin/Python-DBoW3
Author: Ancheng Lin
Author-email: ancheng.lin@ieee.org
License: UNKNOWN
Platform: UNKNOWN
Requires-Dist: numpy
